atsume/__init__.py
atsume/__version__.py
atsume/alembic/__init__.py
atsume/alembic/cli.py
atsume/alembic/config.py
atsume/alembic/exceptions.py
atsume/alembic/template/env.py
atsume/alembic/template/script.py.mako
atsume/bot.py
atsume/cli/__init__.py
atsume/cli/base.py
atsume/cli/component.py
atsume/cli/project.py
atsume/component/__init__.py
atsume/component/component.py
atsume/component/component_config.py
atsume/component/context.py
atsume/component/decorators.py
atsume/component/manager.py
atsume/db/__init__.py
atsume/db/manager.py
atsume/db/models.py
atsume/extensions/__init__.py
atsume/extensions/aiohttp.py
atsume/extensions/loader.py
atsume/extensions/timer.py
atsume/mypy/__init__.py
atsume/mypy/main.py
atsume/mypy/settings.py
atsume/permissions/__init__.py
atsume/permissions/base.py
atsume/permissions/settings_permissions.py
atsume/py.typed
atsume/settings/__init__.py
atsume/settings/default_settings.py
atsume/settings/type_hints.py
atsume/templates/__init__.py
atsume/templates/templates/component/component_name/__init__.py
atsume/templates/templates/component/component_name/apps.py
atsume/templates/templates/component/component_name/commands.py
atsume/templates/templates/component/component_name/models.py
atsume/templates/templates/project/manage.py
atsume/templates/templates/project/project_name/__init__.py
atsume/templates/templates/project/project_name/local.py
atsume/templates/templates/project/project_name/settings.py
atsume/utils.py
hikari_atsume-0.5.1.dist-info/LICENSE
hikari_atsume-0.5.1.dist-info/METADATA
hikari_atsume-0.5.1.dist-info/WHEEL
hikari_atsume-0.5.1.dist-info/entry_points.txt
hikari_atsume-0.5.1.dist-info/RECORD
