Metadata-Version: 2.1
Name: hikari-atsume
Version: 0.5.1
Summary: An opinionated, Django-like Discord bot framework for Hikari, Tanjun, and Ormar
Home-page: https://github.com/pmdevita/hikari-atsume
License: MIT
Keywords: hikari,discord,ormar,tanjun,framework
Author: Peter DeVita
Author-email: mewtwo2643@yahoo.com
Requires-Python: >=3.10,<3.12
Classifier: Framework :: AsyncIO
Classifier: License :: OSI Approved :: MIT License
Classifier: Programming Language :: Python :: 3
Classifier: Programming Language :: Python :: 3.10
Classifier: Programming Language :: Python :: 3.11
Classifier: Topic :: Communications :: Chat
Classifier: Topic :: Internet
Classifier: Topic :: Software Development :: Libraries :: Application Frameworks
Classifier: Typing :: Typed
Provides-Extra: aiopg
Provides-Extra: mariadb
Provides-Extra: mypy
Provides-Extra: mysql
Provides-Extra: postgres
Provides-Extra: postgresql
Provides-Extra: speedups
Provides-Extra: sqlite
Requires-Dist: aiodns (>=3.0.0,<4.0.0) ; extra == "speedups"
Requires-Dist: aiohttp (>=3.8.5,<4.0.0)
Requires-Dist: aiomysql (>=0.2.0,<0.3.0) ; extra == "mysql" or extra == "mariadb"
Requires-Dist: aiopg (>=1.4.0,<2.0.0) ; extra == "aiopg"
Requires-Dist: aiosqlite (>=0.19.0,<0.20.0) ; extra == "sqlite"
Requires-Dist: alembic (>=1.11.1,<2.0.0)
Requires-Dist: asyncpg (>=0.28.0,<0.29.0) ; extra == "postgresql" or extra == "postgres"
Requires-Dist: brotli (>=1.0.9,<2.0.0) ; extra == "speedups"
Requires-Dist: ciso8601 (>=2.3,<3.0) ; extra == "speedups"
Requires-Dist: click (>=8.1.6)
Requires-Dist: hikari (>=2.0.0.dev120,<3.0.0)
Requires-Dist: hikari-tanjun (>=2.15.0,<2.17.0)
Requires-Dist: hupper (>=1.12,<2.0)
Requires-Dist: orjson (>=3.9,<4.0) ; extra == "speedups"
Requires-Dist: ormar (>=0.12.2,<0.13.0)
Requires-Dist: psycopg2-binary (>=2.9.6,<3.0.0) ; extra == "postgresql" or extra == "postgres" or extra == "aiopg"
Requires-Dist: pymysql (>=1.1.0,<2.0.0) ; extra == "mysql" or extra == "mariadb"
Requires-Dist: uvloop (>=0.17,<0.20) ; (sys_platform == "darwin" or sys_platform == "linux") and (extra == "speedups")
Project-URL: Documentation, https://pmdevita.github.io/hikari-atsume/
Project-URL: Repository, https://github.com/pmdevita/hikari-atsume
